climber/__init__.py
climber/climber.py
climber/models.py
climber/summary.py
climber/urls.py
climber/views.py
climber/static/css/climber.css
climber/static/js/climber.js
climber/templates/climber/base.html
climber-0.1.4.dist-info/DESCRIPTION.rst
climber-0.1.4.dist-info/METADATA
climber-0.1.4.dist-info/RECORD
climber-0.1.4.dist-info/WHEEL
climber-0.1.4.dist-info/metadata.json
climber-0.1.4.dist-info/top_level.txt
